MANIFEST.in
README.md
pytest.ini
setup.py
qmap_interpolation/__init__.py
qmap_interpolation/calculate_q_vectors.py
qmap_interpolation/converted_image.py
qmap_interpolation/detector_geometry.py
qmap_interpolation/image.py
qmap_interpolation/instrument.py
qmap_interpolation/q_map.py
qmap_interpolation/typed_tuple.py
qmap_interpolation/units.py
qmap_interpolation/utils.py
qmap_interpolation.egg-info/PKG-INFO
qmap_interpolation.egg-info/SOURCES.txt
qmap_interpolation.egg-info/dependency_links.txt
qmap_interpolation.egg-info/requires.txt
qmap_interpolation.egg-info/top_level.txt
qmap_interpolation/plot/__init__.py
tests/conftest.py