Metadata-Version: 2.1
Name: qmap-interpolation
Version: 0.0.2
Summary: Interpolation of diffraction images to reciprocal space.
Home-page: UNKNOWN
Author: Vladimir Starostin
Author-email: vladimir.starostin@uni-tuebingen.de
License: MIT
Platform: UNKNOWN
Requires-Python: >=3.6.*
